psplay
