Metadata-Version: 2.1
Name: psplay
Version: 0.1.1
Summary: A Jupyter widget for playing with CAR Leaflet maps
Home-page: https://github.com/simonsobs/psplay
Author: Simons Observatory Collaboration Power Spectrum Task Force
License: BSD License
Keywords: CMB,spectra,ipython,jupyter,widgets,graphics
Platform: UNKNOWN
Classifier: Development Status :: 4 - Beta
Classifier: Intended Audience :: Developers
Classifier: Intended Audience :: Science/Research
Classifier: Topic :: Multimedia :: Graphics
Classifier: License :: OSI Approved :: BSD License
Classifier: Programming Language :: Python :: 3.5
Classifier: Programming Language :: Python :: 3.6
Classifier: Programming Language :: Python :: 3.7
Classifier: Programming Language :: Python :: 3.8
Requires-Python: >=3.5
